{
  "name": "Violet Saunders",
  "age": 47,
  "address": {
    "street": "Dajut Plaza",
    "city": "Jedodgi",
    "state": "OH",
    "zip": "72680"
  },
  "contact": {
    "phone": "(825) 347-3680",
    "servicePhone": "800326865"
  },
  "birthday": "1968-08-11T16:14:49.098Z",
  "ip": "108.240.171.251",
  "foo": "bar",
  "profile": {
    "about": "Fabsochi ded izo ejburok jafomun edomizab ibufajuj ubeti dedvabcit nitgecdi ogaowpi roc ri sijab. Ta vat he gujobuk bizoruagi ze ug fa ruvsujgo dov demza woznetzog tibevef inturna vutoma geblib gajak zagritu. Uvivu isza gezwa za ho pen gesot vukrojgid upabu nup fojvi fih.",
    "bio": "Tuw puhugdoj nep invu coh wal pa zafluzo hol icomu usasuzwo ben guni gigunupa gohriba. Kuzkipib funkena julwikuju juttoca ikiemfun leohu net sal zacvesu javak savofu colfe olusuip fivegra zecuji riita. Luwdocma ruz dit feof casruma tuclokwa tohpo nibba javihzis ev nomiju ijojo penhopbom. Ho malfitso mopgafag cerwohed lejif hi vosjofop uhi ka fu famuw dagco ke pozawic sos veud."
  },
  "apiKey": "0f37b0b5fb4d1fc8220f16065d41608f23e37d9d371cbdbb2f18b0cf5d3bff91",
  "currency": {
    "code": "CZK",
    "name": "Czech Republic Koruna"
  }
}