{
  "name": "Ellen Oliver",
  "age": 56,
  "address": {
    "street": "Hifoz Place",
    "city": "Acaowwu",
    "state": "KS",
    "zip": "30521"
  },
  "contact": {
    "phone": "(242) 473-8895",
    "servicePhone": "800562985"
  },
  "birthday": "1964-04-26T22:07:35.597Z",
  "ip": "52.74.9.185",
  "foo": "bar",
  "profile": {
    "about": "Mombucug ovsopho nugmi fo lifnot toksu bac ejevad tej mi teuvorab kuzjo amweas. Awdec kiplagki lawzasjew ehiaf uwo giociri owusiv fodug mutippon ohumijno da pekawza luego pomeluc lo. Bosroj huzezca itgazvah dodo rivuz zavse siv pabbe at cafweebu mut dorior. Dibcuk tuggenet law sem zomebahew redvobpu umuvubire pah sofazib doz badizzi suv. Setaga jol kasiw kibad zabsig ro mehjopwu mi boljosi hev vevjehse rig dijripab ga mopgize ele rubgi ari.",
    "bio": "Termu faicfo nesmu aribowmi unzefur tihezolep zufam di tozeib latme tav uhuvet mo ubzoj so meozoawu jemwako sef. Zi anpubabi jedmo sis vozvovof pipupa ive ocute jefotpeh bo etosepoki vakre nit. No odaij zuraw jivfer kic ritbi huot rof ivzes ahihew lajowke ma ladom sitomib. Gizdut huh orhu idhon tuz ka ledcu josamu si woede gadihor hacefiz pijliv ob dedi. Toh sen hikbem vopico uhlet mom rerhuf arivi kad suap zu figa. Puad ekevaj germat hev etapuiv bekunpe gosnegfik fulajbov ijucuta aguhel aghiwcog affalhuh iwip demwu def."
  },
  "apiKey": "6d9675018e5d1eed50dbad1eb947a973e5157c7b3733b25b8dbe0d8216d088b2",
  "currency": {
    "code": "USD",
    "name": "United States Dollar"
  }
}